antchain_sdk_ak_a1f82644937c486c81a62b0e5a6b4fbe/__init__.py
antchain_sdk_ak_a1f82644937c486c81a62b0e5a6b4fbe/client.py
antchain_sdk_ak_a1f82644937c486c81a62b0e5a6b4fbe/models.py
antchain_ak_a1f82644937c486c81a62b0e5a6b4fbe-1.0.10.dist-info/LICENSE
antchain_ak_a1f82644937c486c81a62b0e5a6b4fbe-1.0.10.dist-info/METADATA
antchain_ak_a1f82644937c486c81a62b0e5a6b4fbe-1.0.10.dist-info/WHEEL
antchain_ak_a1f82644937c486c81a62b0e5a6b4fbe-1.0.10.dist-info/top_level.txt
antchain_ak_a1f82644937c486c81a62b0e5a6b4fbe-1.0.10.dist-info/RECORD
